alchemist/__init__.py
alchemist/client.py
alchemist/exceptions.py
alchemist/session.py
alchemist/utils.py
alchemist_python_sdk-0.0.2.dist-info/licenses/LICENSE
tests/__init__.py
tests/test_client.py
tests/test_exceptions.py
tests/test_session.py
alchemist_python_sdk-0.0.2.dist-info/METADATA
alchemist_python_sdk-0.0.2.dist-info/WHEEL
alchemist_python_sdk-0.0.2.dist-info/top_level.txt
alchemist_python_sdk-0.0.2.dist-info/RECORD
